README.rst
setup.py
assembla/__init__.py
assembla/__main__.py
assembla/api.py
assembla/git.py
assembla/main.py
assembla/space.py
assembla/util.py
assembla_cli.egg-info/PKG-INFO
assembla_cli.egg-info/SOURCES.txt
assembla_cli.egg-info/dependency_links.txt
assembla_cli.egg-info/entry_points.txt
assembla_cli.egg-info/requires.txt
assembla_cli.egg-info/top_level.txt