Metadata-Version: 1.0
Name: assembla-cli
Version: 0.1.1
Summary: A small command-line tool for working with Assembla spaces
Home-page: https://github.com/iBeliever/assembla-cli
Author: Michael Spencer
Author-email: sonrisesoftware@gmail.com
License: UNKNOWN
Platform: UNKNOWN
